EtlWorkers/__init__.py
EtlWorkers/workers/FileWorker.py
EtlWorkers/workers/__init__.py
EtlWorkers-0.0.6.dist-info/LICENSE
EtlWorkers-0.0.6.dist-info/METADATA
EtlWorkers-0.0.6.dist-info/WHEEL
EtlWorkers-0.0.6.dist-info/top_level.txt
EtlWorkers-0.0.6.dist-info/RECORD
