Metadata-Version: 2.1
Name: EtlWorkers
Version: 0.0.6
Summary: A Data Engineering package
Home-page: https://github.com/M-Farag/EtlWorkers
Author: Mina Farag
Author-email: mina.farag@icloud.com
License: UNKNOWN
Platform: UNKNOWN
Classifier: Programming Language :: Python :: 3
Classifier: License :: OSI Approved :: MIT License
Classifier: Operating System :: OS Independent
Requires-Dist: uuid
